ts_deepscan/__init__.py
ts_deepscan/__main__.py
ts_deepscan/cli.py
ts_deepscan/config.py
ts_deepscan/util.py
ts_deepscan/analyser/CachingAnalyser.py
ts_deepscan/analyser/CommentAnalyser.py
ts_deepscan/analyser/CryptoAnalyser.py
ts_deepscan/analyser/Dataset.py
ts_deepscan/analyser/LicenseAnalyser.py
ts_deepscan/analyser/ScanossAnalyser.py
ts_deepscan/analyser/YaraAnalyser.py
ts_deepscan/analyser/__init__.py
ts_deepscan/analyser/licenses.json
ts_deepscan/analyser/spdx.py
ts_deepscan/analyser/scancode/__init__.py
ts_deepscan/analyser/textutils/__init__.py
ts_deepscan/caching/__init__.py
ts_deepscan/commentparser/__init__.py
ts_deepscan/commentparser/language.py
ts_deepscan/scanner/ParallelScanner.py
ts_deepscan/scanner/PoolExecutorScanner.py
ts_deepscan/scanner/PoolScanner.py
ts_deepscan/scanner/Scanner.py
ts_deepscan/scanner/__init__.py
ts_deepscan/scanner/pool/__init__.py
ts_deepscan/scanner/postprocessing/__init__.py
ts_deepscan-2.4.0.dist-info/licenses/LICENSE
ts_deepscan-2.4.0.dist-info/METADATA
ts_deepscan-2.4.0.dist-info/WHEEL
ts_deepscan-2.4.0.dist-info/entry_points.txt
ts_deepscan-2.4.0.dist-info/top_level.txt
ts_deepscan-2.4.0.dist-info/RECORD
