Metadata-Version: 2.4
Name: ts-deepscan
Version: 2.4.0
Summary: Repository scanner for the identification of effective licenses and copyright information.
Author: EACG GmbH
License-Expression: Apache-2.0
Project-URL: Homepage, https://github.com/TrustSource/ts-deepscan.git
Keywords: DeepScan,TrustSource
Requires-Python: <3.13,>=3.10
License-File: LICENSE
Requires-Dist: spacy~=3.8.4
Requires-Dist: nltk~=3.9
Requires-Dist: text-unidecode~=1.3
Requires-Dist: requests~=2.32.3
Requires-Dist: click==8.1.7
Requires-Dist: osadl_matrix==2024.5.22.10535
Requires-Dist: pyminr~=0.1.1; sys_platform != "darwin"
Requires-Dist: pyminr~=0.1.2; sys_platform == "darwin"
Requires-Dist: scancode-toolkit==32.3.2; platform_machine == "x86_64"
Requires-Dist: scancode-toolkit-mini==32.3.2; platform_machine == "arm64"
Requires-Dist: normality<3.0.0
Requires-Dist: dataclasses-json~=0.6.7
Requires-Dist: gitignore-parser~=0.1.11
Requires-Dist: tqdm~=4.67.0
Requires-Dist: scanoss~=1.20.4
Requires-Dist: yara-python~=4.5.0
Requires-Dist: xxhash~=3.6.0
Requires-Dist: diskcache~=5.6.3
Requires-Dist: scanoss~=1.20.4
Dynamic: license-file
